hx_machine_learning_tools/__init__.py
hx_machine_learning_tools/aux_resources/__init__.py
hx_machine_learning_tools/aux_resources/feature_importances/__init__.py
hx_machine_learning_tools/aux_resources/graphics/__init__.py
hx_machine_learning_tools/aux_resources/hx_model_evaluation_and_metrics/__init__.py
hx_machine_learning_tools/aux_resources/hx_model_evaluation_and_metrics/classifiers.py
hx_machine_learning_tools/aux_resources/hx_model_evaluation_and_metrics/regressors.py
hx_machine_learning_tools/aux_resources/shap/__init__.py
hx_machine_learning_tools/base_model/__init__.py
hx_machine_learning_tools/classifier_models/HxCatBoostClassifier.py
hx_machine_learning_tools/classifier_models/HxLightGbmClassifier.py
hx_machine_learning_tools/classifier_models/HxRandomForestClassifier.py
hx_machine_learning_tools/classifier_models/HxXtremeGradientBoostingClassifier.py
hx_machine_learning_tools/classifier_models/__init__.py
hx_machine_learning_tools/regressor_models/HxCatBoostRegressor.py
hx_machine_learning_tools/regressor_models/HxLightGbmRegressor.py
hx_machine_learning_tools/regressor_models/HxXtremeGradientBoostingRegressor.py
hx_machine_learning_tools/regressor_models/__init__.py
scikit_learn_tools/__init__.py
hx_machine_learning_tools-2025.9.25.dist-info/METADATA
hx_machine_learning_tools-2025.9.25.dist-info/WHEEL
hx_machine_learning_tools-2025.9.25.dist-info/top_level.txt
hx_machine_learning_tools-2025.9.25.dist-info/RECORD
