Metadata-Version: 2.4
Name: hx_machine_learning_tools
Version: 2025.9.25
Summary: Librería de utilidades de modelos de machine learning
Home-page: https://github.com/Huexmaister/hx_machine_learning_tools
Author: Daniel Sarabia aka Huexmaister
Author-email: dsarabiatorres@gmail.com
Classifier: Programming Language :: Python :: 3
Classifier: License :: OSI Approved :: MIT License
Classifier: Operating System :: OS Independent
Requires-Python: >=3.10
Requires-Dist: catboost==1.2.8
Requires-Dist: category_encoders==2.8.1
Requires-Dist: constants_and_tools==1.1.2
Requires-Dist: imbalanced-learn==0.14.0
Requires-Dist: imblearn==0.0
Requires-Dist: joblib==1.5.2
Requires-Dist: scikit-learn==1.7.2
Requires-Dist: shap==0.48.0
Requires-Dist: xgboost==3.0.5
Requires-Dist: lightgbm==4.6.0
Dynamic: author
Dynamic: author-email
Dynamic: classifier
Dynamic: description
Dynamic: description-content-type
Dynamic: home-page
Dynamic: requires-dist
Dynamic: requires-python
Dynamic: summary
